agentmemory/__init__.py
agentmemory/check_model.py
agentmemory/client.py
agentmemory/clustering.py
agentmemory/events.py
agentmemory/helpers.py
agentmemory/main.py
agentmemory/persistence.py
agentmemory/postgres.py
agentmemory-0.4.7.dist-info/LICENSE
agentmemory-0.4.7.dist-info/METADATA
agentmemory-0.4.7.dist-info/WHEEL
agentmemory-0.4.7.dist-info/top_level.txt
agentmemory-0.4.7.dist-info/RECORD
