Metadata-Version: 2.1
Name: agentmemory
Version: 0.4.7
Summary: Easy-to-use memory for agents, document search, knowledge graphing and more.
Home-page: https://github.com/AutonomousResearchGroup/agentmemory
Author: Moon
Author-email: shawmakesmagic@gmail.com
License: MIT
Classifier: Development Status :: 4 - Beta
Classifier: Intended Audience :: Science/Research
Classifier: License :: OSI Approved :: MIT License
Classifier: Operating System :: POSIX :: Linux
Classifier: Programming Language :: Python :: 3
Classifier: Operating System :: MacOS :: MacOS X
Classifier: Operating System :: Microsoft :: Windows
License-File: LICENSE
Requires-Dist: chromadb
Requires-Dist: agentlogger
Requires-Dist: psycopg2-binary
Requires-Dist: python-dotenv
